weixinauto/__init__.py
weixinauto/wechat.py
weixinauto/domain/__init__.py
weixinauto/domain/license_manager.py
weixinauto/infra/__init__.py
weixinauto/infra/uia/__init__.py
weixinauto/infra/uia/avatar_clicker.py
weixinauto/infra/uia/chat_listener.py
weixinauto/infra/uia/chat_listener.pyi
weixinauto/infra/uia/chat_listener_back.py
weixinauto/infra/uia/clipboard_utils.py
weixinauto/infra/uia/message.py
weixinauto/infra/uia/message.pyi
weixinauto/infra/uia/message_actions.py
weixinauto/infra/uia/message_extract.py
weixinauto/infra/uia/message_extract.pyi
weixinauto/infra/uia/nickname_reader.py
weixinauto/infra/uia/sender_click_resolver.py
weixinauto/infra/uia/uia_probe.py
weixinauto/infra/uia/uia_subscription.py
weixinauto/infra/uia/utils_win.py
weixinauto/infra/uia/wechat_driver.py
weixinauto/infra/uia/wechat_driver.pyi
weixinauto/infra/uia/weixin_login.py
weixinauto/infra/uia/weixin_newmessage.py
weixinauto/infra/uia/weixin_newmessage.pyi
weixinauto/infra/uia/weixin_newmessage_back.py
weixinauto/infra/uia/win32helpers.py
weixinauto/infra/uia/wx_chat_finder.py
weixinauto/infra/uia/wx_subwindow_ops.py
weixinauto/infra/uia/pyarmor_runtime_009672/__init__.py
weixinauto/infra/uia/pyarmor_runtime_009672/pyarmor_runtime.pyd
weixinauto/infra/uia/selectors/__init__.py
weixinauto/infra/uia/selectors/resolver.py
weixinauto/infra/uia/selectors/wechat_4_1_plus.json
weixinauto/secure/__init__.py
weixinauto/secure/license_core.cp311-win_amd64.pyd
weixinautox4-2.2.3.1.dist-info/METADATA
weixinautox4-2.2.3.1.dist-info/WHEEL
weixinautox4-2.2.3.1.dist-info/top_level.txt
weixinautox4-2.2.3.1.dist-info/RECORD
