Metadata-Version: 2.4
Name: weixinautox4
Version: 2.2.3.1
Summary: WeChat automation SDK with license management.
Author: agentaibot
Author-email: zhilongfeng66@gmail.com
Classifier: Programming Language :: Python :: 3.11
Classifier: License :: OSI Approved :: MIT License
Classifier: Operating System :: Microsoft :: Windows
Requires-Python: >=3.11,<3.12
Requires-Dist: requests>=2.24.0
Requires-Dist: Cython>=0.29.21
Requires-Dist: pydantic>=1.8.2
Requires-Dist: Pillow>=9.0.0
Requires-Dist: pywin32==311
Requires-Dist: uiautomation==2.0.29
Dynamic: author
Dynamic: author-email
Dynamic: classifier
Dynamic: requires-dist
Dynamic: requires-python
Dynamic: summary
